{
    "verbosity": 0,
    "userid": "thomasg",
    "geographic": true,
    "timeseries": false,
    "locus": "tovetorp2022-ngs-dried",
    "campaignshortid": "tovetorp2022",
    "campaignuuid": "53a3862e-afa6-11ed-8f5c-98455a9fde21",
    "importversion": "importxspectrev089",
    "muzzleid": "1205VINI",
    "graphics": {
        "raw-spectra": {
            "show": true,
            "save": true,
            "dark": true,
            "variation": true,
            "signalstyle": {
                "color": "blue",
                "variationopacity": 0.5
            },
            "darkstyle": {
                "color": "black",
                "variationopacity": 0.5
            }
        },
        "reflectance-spectra": {
            "show": true,
            "save": true,
            "whiteref": "latest",
            "variation": true,
            "signalstyle": {
                "color": "blue",
                "variationopacity": 0.5
            },
            "darkstyle": {
                "color": "black",
                "variationopacity": 0.5
            }
        },
        "probe-results": {
            "show": true,
            "save": false,
            "variation": true,
            "signalstyle": {
                "color": "blue",
                "variationopacity": 0.5
            }
        }
    },
    "sampling": {
        "theme": "soil",
        "family": "ag",
        "species": "",
        "brand": "",
        "version": "0",
        "subsample": "0",
        "depth": -99,
        "prepcode": "dry+sieve",
        "scan": "1",
        "mode": "default",
        "sampledate": "20221001"
    },
    "c14384ma-01": {
        "samplerepeats": 6,
        "darkrepeats": 2,
        "headtrail": 1,
        "warmup": 0,
        "maxDN": 880,
        "fetchReference": 0,
        "parameters": {
            "LED_mset_mV": 2900,
            "stabilistaiontime": 50,
            "fetchscantuning": 1,
            "scantuning": {
                "nIntegrationTimes": 4,
                "integrationtimes": {
                    "0": [
                        6,
                        111,
                        157
                    ],
                    "1": [
                        14,
                        82,
                        187
                    ],
                    "2": [
                        45,
                        78,
                        215
                    ],
                    "3": [
                        200,
                        64,
                        256
                    ]
                }
            }
        }
    },
    "scandate": "20240109",
    "source": "Hamamatsu C14384MA-01",
    "sensorid": "c14384ma-01",
    "product": "raw-spectra",
    "sampleid": "7-35-40-a",
    "xparams": {
        "sensor": "c14384ma-01",
        "samplerepeats": 6,
        "darkrepeats": 2,
        "headtrail": 1,
        "warmup": 0,
        "maxDN": 880,
        "muzzle": "1206VINI",
        "Vin": 2900,
        "stabilisationTime": 50,
        "nIntegrationTimes": 4,
        "0": [
            6,
            111,
            157
        ],
        "1": [
            14,
            82,
            187
        ],
        "2": [
            45,
            78,
            215
        ],
        "3": [
            200,
            64,
            256
        ]
    },
    "wavelength": [
        546.89,
        551.6,
        556.29,
        560.96,
        565.62,
        570.26,
        574.88,
        579.48,
        584.07,
        588.65,
        593.2,
        597.74,
        602.26,
        606.77,
        611.26,
        615.73,
        620.18,
        624.62,
        629.04,
        633.44,
        637.82,
        642.19,
        646.54,
        650.87,
        655.19,
        659.49,
        663.77,
        668.03,
        672.27,
        676.5,
        680.71,
        684.9,
        689.07,
        693.23,
        697.36,
        701.48,
        705.58,
        709.66,
        713.73,
        717.77,
        721.8,
        725.8,
        729.79,
        733.76,
        737.71,
        741.65,
        745.56,
        749.45,
        753.33,
        757.19,
        761.02,
        764.84,
        768.64,
        772.42,
        776.18,
        779.92,
        783.64,
        787.34,
        791.02,
        794.68,
        798.32,
        801.94,
        805.54,
        809.12,
        812.69,
        816.23,
        819.75,
        823.25,
        826.73,
        830.19,
        833.63,
        837.05,
        840.45,
        843.83,
        847.19,
        850.53,
        853.84,
        857.14,
        860.42,
        863.67,
        866.91,
        870.12,
        873.32,
        876.49,
        879.64,
        882.77,
        885.88,
        888.97,
        892.04,
        895.09,
        898.12,
        901.12,
        904.11,
        907.07,
        910.02,
        912.94,
        915.84,
        918.72,
        921.59,
        924.43,
        927.25,
        930.04,
        932.82,
        935.58,
        938.32,
        941.03,
        943.73,
        946.4,
        949.06,
        951.69,
        954.31,
        956.9,
        959.48,
        962.03,
        964.56,
        967.08,
        969.57,
        972.04,
        974.5,
        976.93,
        979.35,
        981.74,
        984.12,
        986.48,
        988.81,
        991.13,
        993.43,
        995.71,
        997.97,
        1000.22,
        1002.44,
        1004.65,
        1006.84,
        1009.01,
        1011.16,
        1013.3,
        1015.42,
        1017.52,
        1019.6,
        1021.67,
        1023.72,
        1025.75,
        1027.77,
        1029.77,
        1031.75,
        1033.72,
        1035.67,
        1037.61,
        1039.53,
        1041.44,
        1043.33,
        1045.21,
        1047.07,
        1048.92,
        1050.76,
        1052.58,
        1054.39,
        1056.19,
        1057.97,
        1059.74,
        1061.5,
        1063.25,
        1064.99,
        1066.71,
        1068.43,
        1070.13,
        1071.83,
        1073.51,
        1075.19,
        1076.85,
        1078.51,
        1080.16,
        1081.8,
        1083.43,
        1085.05,
        1086.67,
        1088.28,
        1089.89,
        1091.49,
        1093.09,
        1094.67,
        1096.26,
        1097.84,
        1099.42,
        1100.99,
        1102.57,
        1104.14,
        1105.7,
        1107.27,
        1108.84,
        1110.4,
        1111.97
    ],
    "samplemean": [
        162.0,
        167.5,
        167.67,
        165.83,
        174.0,
        193.33,
        209.5,
        187.33,
        170.67,
        170.5,
        171.5,
        171.33,
        177.33,
        190.33,
        125.0,
        140.0,
        162.83,
        201.83,
        149.33,
        163.5,
        175.5,
        181.33,
        189.33,
        192.5,
        194.17,
        192.83,
        195.33,
        191.67,
        188.0,
        186.0,
        185.67,
        182.17,
        182.0,
        182.5,
        182.83,
        188.33,
        189.67,
        196.17,
        205.33,
        215.5,
        228.17,
        242.33,
        261.17,
        277.83,
        297.5,
        315.0,
        331.83,
        232.5,
        236.5,
        241.5,
        251.0,
        257.67,
        259.17,
        259.5,
        264.83,
        264.67,
        273.33,
        266.83,
        268.83,
        270.33,
        261.83,
        259.0,
        261.17,
        252.33,
        247.83,
        246.67,
        241.67,
        242.83,
        237.83,
        233.0,
        232.33,
        227.67,
        225.83,
        225.17,
        224.83,
        222.0,
        216.17,
        219.33,
        213.17,
        214.33,
        204.83,
        209.5,
        209.17,
        208.0,
        205.83,
        207.83,
        203.17,
        199.67,
        201.33,
        198.67,
        198.17,
        199.33,
        197.17,
        274.33,
        272.83,
        272.17,
        267.83,
        267.0,
        263.0,
        264.0,
        260.33,
        252.67,
        250.33,
        244.17,
        242.33,
        238.33,
        235.17,
        231.33,
        224.67,
        222.17,
        218.33,
        211.67,
        207.17,
        204.5,
        200.33,
        196.83,
        194.17,
        187.83,
        182.67,
        181.67,
        175.33,
        172.0,
        170.5,
        289.83,
        280.17,
        270.33,
        263.17,
        252.17,
        244.67,
        238.17,
        229.33,
        227.67,
        217.0,
        209.83,
        203.67,
        198.67,
        191.83,
        187.67,
        183.83,
        181.67,
        174.83,
        169.83,
        165.5,
        162.33,
        162.17,
        158.33,
        154.83,
        151.17,
        149.17,
        144.67,
        144.67,
        279.5,
        271.33,
        261.17,
        258.5,
        250.67,
        244.67,
        236.83,
        231.33,
        225.83,
        219.5,
        213.17,
        210.83,
        208.17,
        205.0,
        200.17,
        197.33,
        193.5,
        188.33,
        187.33,
        185.0,
        183.83,
        181.17,
        178.67,
        176.33,
        175.67,
        174.67,
        173.67,
        171.5,
        171.17,
        168.33,
        167.17,
        164.17,
        163.83,
        161.0,
        155.83,
        157.33,
        157.33,
        155.0,
        157.83,
        153.83,
        152.67
    ],
    "samplestd": [
        1.15,
        2.57,
        0.75,
        0.69,
        2.38,
        1.37,
        2.14,
        2.21,
        1.25,
        2.06,
        1.26,
        1.11,
        1.25,
        1.11,
        1.15,
        1.0,
        1.77,
        1.34,
        4.68,
        1.38,
        0.96,
        6.99,
        1.7,
        5.47,
        0.9,
        1.57,
        3.14,
        0.94,
        1.29,
        1.15,
        0.47,
        1.46,
        1.41,
        1.89,
        0.69,
        1.6,
        1.11,
        1.21,
        2.29,
        1.61,
        1.67,
        3.68,
        2.54,
        2.54,
        3.86,
        1.29,
        2.03,
        1.89,
        1.5,
        1.38,
        5.07,
        1.8,
        2.11,
        5.16,
        1.07,
        1.8,
        8.84,
        1.57,
        1.86,
        3.09,
        2.34,
        1.41,
        9.82,
        0.75,
        1.77,
        0.94,
        2.36,
        1.07,
        1.07,
        4.16,
        1.7,
        1.37,
        4.67,
        2.73,
        2.48,
        2.24,
        6.47,
        7.02,
        2.54,
        4.89,
        6.96,
        0.96,
        1.77,
        1.73,
        1.07,
        5.64,
        1.07,
        2.81,
        1.11,
        1.89,
        1.77,
        1.97,
        4.14,
        3.09,
        2.03,
        1.67,
        2.54,
        2.58,
        1.83,
        2.77,
        1.37,
        3.5,
        1.37,
        3.39,
        1.8,
        0.75,
        1.34,
        2.56,
        1.11,
        1.34,
        4.07,
        3.09,
        1.21,
        4.86,
        1.11,
        1.95,
        2.11,
        1.67,
        1.37,
        8.28,
        0.94,
        1.41,
        1.8,
        1.77,
        1.07,
        2.21,
        3.48,
        2.03,
        1.49,
        1.34,
        1.97,
        5.96,
        1.83,
        2.67,
        1.25,
        0.47,
        1.77,
        1.8,
        1.95,
        3.54,
        1.46,
        0.9,
        1.26,
        0.94,
        8.51,
        1.37,
        1.07,
        1.34,
        0.69,
        1.37,
        1.11,
        1.71,
        2.92,
        1.07,
        2.29,
        3.2,
        1.37,
        0.69,
        1.7,
        1.34,
        2.22,
        1.95,
        2.11,
        1.67,
        5.07,
        1.34,
        1.89,
        2.5,
        0.94,
        1.11,
        1.15,
        1.34,
        1.95,
        1.49,
        0.47,
        0.75,
        1.49,
        2.21,
        1.61,
        0.69,
        1.11,
        0.9,
        1.07,
        1.57,
        1.0,
        2.11,
        0.75,
        0.75,
        2.71,
        1.67,
        1.07,
        1.89
    ],
    "darkmean": [
        99.5,
        99.5,
        97.0,
        95.5,
        96.5,
        96.5,
        99.0,
        99.5,
        99.0,
        98.5,
        98.5,
        98.0,
        100.5,
        100.0,
        98.0,
        98.5,
        99.5,
        101.5,
        101.5,
        99.0,
        101.0,
        101.0,
        103.0,
        103.0,
        100.5,
        101.5,
        102.0,
        102.5,
        102.0,
        100.5,
        102.5,
        103.0,
        102.0,
        103.5,
        102.0,
        104.5,
        102.5,
        100.5,
        102.5,
        102.5,
        104.0,
        101.5,
        103.0,
        100.5,
        104.0,
        103.5,
        104.0,
        104.5,
        102.5,
        103.5,
        104.0,
        105.0,
        104.5,
        106.5,
        104.5,
        106.0,
        105.5,
        106.5,
        104.5,
        106.0,
        105.5,
        105.5,
        105.5,
        104.5,
        102.5,
        105.0,
        103.0,
        104.0,
        105.0,
        105.5,
        107.0,
        104.5,
        106.0,
        104.5,
        105.5,
        102.5,
        103.5,
        103.5,
        104.5,
        103.0,
        102.5,
        106.0,
        103.5,
        104.0,
        103.5,
        103.0,
        104.0,
        102.0,
        101.5,
        103.5,
        102.0,
        104.0,
        102.5,
        100.5,
        101.0,
        100.5,
        102.0,
        102.0,
        100.0,
        102.0,
        101.0,
        101.0,
        100.0,
        101.5,
        101.5,
        100.5,
        100.5,
        99.0,
        100.0,
        100.5,
        99.5,
        99.0,
        99.0,
        101.0,
        99.5,
        99.0,
        101.0,
        99.5,
        99.5,
        100.0,
        99.0,
        100.5,
        97.0,
        98.0,
        99.5,
        100.0,
        100.5,
        101.0,
        99.0,
        99.0,
        97.5,
        98.5,
        100.0,
        99.5,
        99.0,
        99.0,
        98.5,
        99.5,
        99.0,
        98.5,
        98.5,
        97.5,
        97.5,
        97.5,
        98.0,
        98.5,
        98.5,
        97.5,
        98.5,
        99.0,
        98.0,
        101.0,
        101.0,
        100.5,
        99.5,
        100.0,
        99.0,
        100.5,
        101.0,
        99.5,
        101.0,
        101.0,
        100.0,
        101.0,
        99.0,
        100.5,
        99.5,
        101.0,
        99.0,
        100.5,
        99.5,
        98.5,
        98.0,
        99.5,
        100.0,
        101.0,
        97.5,
        99.5,
        100.0,
        100.5,
        99.5,
        99.0,
        99.5,
        99.5,
        99.5,
        98.5,
        98.5,
        98.0,
        97.5,
        99.0,
        100.0,
        100.0
    ],
    "darkstd": [
        0.5,
        1.5,
        0.0,
        0.5,
        0.5,
        0.5,
        0.0,
        0.5,
        0.0,
        0.5,
        0.5,
        0.0,
        0.5,
        0.0,
        2.0,
        0.5,
        0.5,
        0.5,
        0.5,
        1.0,
        1.0,
        0.0,
        1.0,
        1.0,
        1.5,
        1.5,
        2.0,
        0.5,
        1.0,
        1.5,
        0.5,
        0.0,
        1.0,
        0.5,
        2.0,
        1.5,
        0.5,
        0.5,
        0.5,
        0.5,
        1.0,
        0.5,
        0.0,
        1.5,
        0.0,
        0.5,
        1.0,
        1.5,
        0.5,
        0.5,
        1.0,
        0.0,
        0.5,
        1.5,
        0.5,
        1.0,
        0.5,
        0.5,
        0.5,
        1.0,
        0.5,
        0.5,
        0.5,
        1.5,
        0.5,
        0.0,
        1.0,
        0.0,
        1.0,
        0.5,
        1.0,
        0.5,
        2.0,
        0.5,
        0.5,
        0.5,
        0.5,
        0.5,
        0.5,
        0.0,
        0.5,
        1.0,
        0.5,
        0.0,
        0.5,
        0.0,
        0.0,
        1.0,
        0.5,
        0.5,
        1.0,
        1.0,
        1.5,
        1.5,
        1.0,
        0.5,
        1.0,
        1.0,
        1.0,
        0.0,
        1.0,
        0.0,
        0.0,
        0.5,
        0.5,
        0.5,
        0.5,
        0.0,
        0.0,
        1.5,
        0.5,
        1.0,
        0.0,
        0.0,
        0.5,
        1.0,
        1.0,
        0.5,
        0.5,
        0.0,
        0.0,
        1.5,
        0.0,
        0.0,
        0.5,
        1.0,
        0.5,
        1.0,
        1.0,
        0.0,
        0.5,
        0.5,
        0.0,
        0.5,
        1.0,
        0.0,
        0.5,
        0.5,
        1.0,
        0.5,
        0.5,
        0.5,
        0.5,
        0.5,
        0.0,
        1.5,
        0.5,
        0.5,
        0.5,
        1.0,
        1.0,
        1.0,
        0.0,
        1.5,
        0.5,
        0.0,
        0.0,
        0.5,
        1.0,
        0.5,
        0.0,
        1.0,
        0.0,
        2.0,
        0.0,
        0.5,
        0.5,
        1.0,
        1.0,
        0.5,
        1.5,
        0.5,
        0.0,
        0.5,
        1.0,
        1.0,
        0.5,
        0.5,
        1.0,
        0.5,
        0.5,
        1.0,
        0.5,
        0.5,
        1.5,
        0.5,
        0.5,
        0.0,
        0.5,
        1.0,
        1.0,
        1.0
    ]
}